{
  "headers": {
    "x-amz-cf-pop": "FRA56-P5",
    "x-amz-replication-status": "COMPLETED",
    "x-frame-options": "DENY",
    "x-amz-version-id": "TGInjO6p546Irq_p482nskNuKNp1kKjk",
    "x-cache": "Hit from cloudfront",
    "x-content-type-options": "nosniff",
    "content-length": "2449",
    "server-timing": "fetchSource;dur=16",
    "last-modified": "Fri, 25 Mar 2022 13:32:50 GMT",
    "accept-ranges": "bytes",
    "access-control-allow-origin": "*",
    "server": "deno/gcp-europe-west3",
    "content-type": "application/typescript; charset=utf-8",
    "cross-origin-opener-policy": "same-origin",
    "cache-control": "public, max-age=31536000, immutable",
    "content-security-policy": "default-src 'none'; style-src 'unsafe-inline'; sandbox",
    "cross-origin-embedder-policy": "same-origin",
    "cross-origin-resource-policy": "same-origin",
    "date": "Wed, 27 Dec 2023 23:21:10 GMT",
    "age": "20428502",
    "etag": "\"0dd9cf5f028ceb08ccd43fb1ec79f2db\"",
    "referrer-policy": "strict-origin-when-cross-origin",
    "vary": "Accept-Encoding, Origin",
    "via": "http/2 edgeproxy-h",
    "x-amz-cf-id": "LU9pOjF9tmmVf1y1WDzoir7Cky2ezfn1VCjszsNrVLfQA3blRDnT0w==",
    "strict-transport-security": "max-age=63072000; includeSubDomains; preload"
  },
  "url": "https://deno.land/std@0.132.0/node/internal_binding/_utils.ts",
  "now": {
    "secs_since_epoch": 1724147771,
    "nanos_since_epoch": 35249573
  }
}